MANIFEST.in
README.md
setup.py
my_package/__init__.py
my_package/__main__.py
my_package_chetan.egg-info/PKG-INFO
my_package_chetan.egg-info/SOURCES.txt
my_package_chetan.egg-info/dependency_links.txt
my_package_chetan.egg-info/entry_points.txt
my_package_chetan.egg-info/top_level.txt